<annotation>
	<folder>livelong</folder>
	<filename>livelong.35e15e94-f474-11ef-b21c-c6da1e7226b4.jpg</filename>
	<path>/Volumes/Mohs's_SSD/DeepLearning Models/DataSets/Images_OD/livelong/livelong.35e15e94-f474-11ef-b21c-c6da1e7226b4.jpg</path>
	<source>
		<database>Unknown</database>
	</source>
	<size>
		<width>1920</width>
		<height>1080</height>
		<depth>3</depth>
	</size>
	<segmented>0</segmented>
	<object>
		<name>LiveLong</name>
		<pose>Unspecified</pose>
		<truncated>0</truncated>
		<difficult>0</difficult>
		<bndbox>
			<xmin>1054</xmin>
			<ymin>521</ymin>
			<xmax>1344</xmax>
			<ymax>876</ymax>
		</bndbox>
	</object>
</annotation>
